prism/__init__.py
prism/cli.py
prism/executor.py
prism/manager.py
prism/project.py
prism/rules.py
prism/tui.py
prism/utils.py
prism_sweep-0.2.0.dist-info/licenses/LICENSE
prism_sweep-0.2.0.dist-info/METADATA
prism_sweep-0.2.0.dist-info/WHEEL
prism_sweep-0.2.0.dist-info/entry_points.txt
prism_sweep-0.2.0.dist-info/top_level.txt
prism_sweep-0.2.0.dist-info/RECORD
