Metadata-Version: 2.4
Name: prism-sweep
Version: 0.2.0
Summary: PRISM - Parameter Research & Investigation Sweep Manager
Author-email: Francesco Correnti <fcorrenti2000@gmail.com>
Maintainer-email: Francesco Correnti <fcorrenti2000@gmail.com>
License: MIT
Project-URL: Homepage, https://github.com/FrancescoCorrenti/prism-sweep
Project-URL: Documentation, https://github.com/FrancescoCorrenti/prism-sweep#readme
Project-URL: Repository, https://github.com/FrancescoCorrenti/prism-sweep
Keywords: machine-learning,experiment-management,hyperparameter-sweep,mlops
Classifier: Development Status :: 4 - Beta
Classifier: Intended Audience :: Developers
Classifier: Intended Audience :: Science/Research
Classifier: Operating System :: OS Independent
Classifier: Programming Language :: Python :: 3
Classifier: Programming Language :: Python :: 3.8
Classifier: Programming Language :: Python :: 3.9
Classifier: Programming Language :: Python :: 3.10
Classifier: Programming Language :: Python :: 3.11
Classifier: Programming Language :: Python :: 3.12
Classifier: Topic :: Scientific/Engineering :: Artificial Intelligence
Requires-Python: >=3.8
License-File: LICENSE
Requires-Dist: pyyaml>=6.0
Requires-Dist: rich>=12.0
Provides-Extra: dev
Requires-Dist: pytest>=7.0; extra == "dev"
Requires-Dist: black>=22.0; extra == "dev"
Requires-Dist: isort>=5.0; extra == "dev"
Dynamic: license-file
